{
	"276329924447698946": {
		"amounts": {
			"toastTime": 5,
			"checkInterval": 10
		},
		"dates": {
			"logDate": {}
		},
		"defaultSettings": {
			"custom": 1,
			"dnd": 1,
			"idle": 1,
			"listening": 1,
			"mobile": 1,
			"offline": 1,
			"online": 1,
			"playing": 1,
			"streaming": 1
		},
		"general": {
			"addOnlineCount": false,
			"showDiscriminator": false,
			"muteOnDND": true,
			"openOnClick": true
		},
		"notificationSounds": {
			"toastonline": {
				"url": null,
				"song": null,
				"mute": false
			},
			"desktoponline": {
				"url": null,
				"song": null,
				"mute": true
			},
			"toastidle": {
				"url": null,
				"song": null,
				"mute": false
			},
			"desktopidle": {
				"url": null,
				"song": null,
				"mute": false
			},
			"toastdnd": {
				"url": null,
				"song": null,
				"mute": false
			},
			"desktopdnd": {
				"url": null,
				"song": null,
				"mute": false
			},
			"toastplaying": {
				"url": null,
				"song": null,
				"mute": false
			},
			"desktopplaying": {
				"url": null,
				"song": null,
				"mute": false
			},
			"toastlistening": {
				"url": null,
				"song": null,
				"mute": false
			},
			"desktoplistening": {
				"url": null,
				"song": null,
				"mute": false
			},
			"toaststreaming": {
				"url": null,
				"song": null,
				"mute": false
			},
			"desktopstreaming": {
				"url": null,
				"song": null,
				"mute": false
			},
			"toastoffline": {
				"url": null,
				"song": null,
				"mute": false
			},
			"desktopoffline": {
				"url": null,
				"song": null,
				"mute": false
			}
		},
		"notificationStrings": {
			"online": "$user changed status to '$status'",
			"idle": "$user changed status to '$status'",
			"dnd": "$user changed status to '$status'",
			"playing": "$user started playing '$game'",
			"listening": "$user started listening to '$song'",
			"streaming": "$user started streaming '$game'",
			"offline": "$user changed status to '$status'",
			"login": "$user just logged in '$status'",
			"custom": "$user changed status to '$custom'"
		},
		"observed": {
			"276329924447698946": {
				"friends": {
					"401438416686022666": {
						"online": 1,
						"idle": 1,
						"dnd": 1,
						"playing": 1,
						"listening": 1,
						"streaming": 1,
						"offline": 1,
						"login": 0,
						"mobile": 1,
						"custom": 1,
						"timelog": true
					},
					"428156760268865547": {
						"online": 1,
						"idle": 1,
						"dnd": 1,
						"playing": 1,
						"listening": 1,
						"streaming": 1,
						"offline": 1,
						"login": 0,
						"mobile": 1,
						"custom": 1,
						"timelog": true
					},
					"438373551821553674": {
						"online": 1,
						"idle": 1,
						"dnd": 1,
						"playing": 1,
						"listening": 1,
						"streaming": 1,
						"offline": 1,
						"login": 0,
						"mobile": 1,
						"custom": 1,
						"timelog": true
					},
					"444588957351542784": {
						"online": 1,
						"idle": 1,
						"dnd": 1,
						"playing": 1,
						"listening": 1,
						"streaming": 1,
						"offline": 1,
						"login": 0,
						"mobile": 1,
						"custom": 1,
						"timelog": true
					},
					"454981774754185218": {
						"online": 1,
						"idle": 1,
						"dnd": 1,
						"playing": 1,
						"listening": 1,
						"streaming": 1,
						"offline": 1,
						"login": 0,
						"mobile": 1,
						"custom": 1,
						"timelog": true
					},
					"691175890004082698": {
						"online": 1,
						"idle": 1,
						"dnd": 1,
						"playing": 1,
						"listening": 1,
						"streaming": 1,
						"offline": 1,
						"login": 0,
						"mobile": 1,
						"custom": 1,
						"timelog": true
					},
					"690176399478489109": {
						"online": 1,
						"idle": 1,
						"dnd": 1,
						"playing": 1,
						"listening": 1,
						"streaming": 1,
						"offline": 1,
						"login": 0,
						"mobile": 1,
						"custom": 1,
						"timelog": true
					},
					"462119748692606987": {
						"online": 1,
						"idle": 1,
						"dnd": 1,
						"playing": 1,
						"listening": 1,
						"streaming": 1,
						"offline": 1,
						"login": 0,
						"mobile": 1,
						"custom": 1,
						"timelog": true
					},
					"444223135940739083": {
						"online": 1,
						"idle": 1,
						"dnd": 1,
						"playing": 1,
						"listening": 1,
						"streaming": 1,
						"offline": 1,
						"login": 0,
						"mobile": 1,
						"custom": 1,
						"timelog": true
					},
					"617247386409893900": {
						"online": 1,
						"idle": 1,
						"dnd": 1,
						"playing": 1,
						"listening": 1,
						"streaming": 1,
						"offline": 1,
						"login": 0,
						"mobile": 1,
						"custom": 1,
						"timelog": true
					},
					"473157580747702273": {
						"online": 1,
						"idle": 1,
						"dnd": 1,
						"playing": 1,
						"listening": 1,
						"streaming": 1,
						"offline": 1,
						"login": 0,
						"mobile": 1,
						"custom": 1,
						"timelog": true
					},
					"349870489700925440": {
						"online": 1,
						"idle": 1,
						"dnd": 1,
						"playing": 1,
						"listening": 1,
						"streaming": 1,
						"offline": 1,
						"login": 0,
						"mobile": 1,
						"custom": 1,
						"timelog": true
					},
					"478991912574124032": {
						"online": 1,
						"idle": 1,
						"dnd": 1,
						"playing": 1,
						"listening": 1,
						"streaming": 1,
						"offline": 1,
						"login": 0,
						"mobile": 1,
						"custom": 1,
						"timelog": true
					},
					"927744068979683349": {
						"online": 1,
						"idle": 1,
						"dnd": 1,
						"playing": 1,
						"listening": 1,
						"streaming": 1,
						"offline": 1,
						"login": 0,
						"mobile": 1,
						"custom": 1,
						"timelog": true
					},
					"415880216515313677": {},
					"596622031840083979": {},
					"578674706581028874": {}
				},
				"strangers": {
					"undefined": {
						"online": 0,
						"idle": 0,
						"disabled": false
					},
					"696224867371974717": {
						"online": 1,
						"idle": 1,
						"dnd": 1,
						"playing": 1,
						"listening": 1,
						"streaming": 1,
						"offline": 1,
						"mobile": 1,
						"custom": 1
					},
					"478538300106342413": {
						"online": 1,
						"idle": 1,
						"dnd": 1,
						"playing": 1,
						"listening": 1,
						"streaming": 1,
						"offline": 1,
						"mobile": 1,
						"custom": 1,
						"disabled": false
					},
					"509063374320173066": {
						"idle": 1,
						"online": 1,
						"dnd": 1,
						"playing": 1,
						"listening": 1,
						"streaming": 1,
						"offline": 1,
						"mobile": 1,
						"custom": 1
					},
					"409009312896253953": {},
					"436952515427303426": {},
					"462664124695052298": {},
					"719207689808379905": {
						"online": 1,
						"idle": 1,
						"dnd": 1,
						"playing": 1,
						"listening": 1,
						"streaming": 1,
						"offline": 1,
						"login": 0,
						"mobile": 1,
						"custom": 1,
						"timelog": true
					}
				}
			},
			"friends": {
				"349870489700925440": {},
				"401438416686022666": {},
				"415880216515313677": {},
				"428156760268865547": {},
				"438373551821553674": {},
				"444223135940739083": {},
				"444588957351542784": {},
				"454981774754185218": {},
				"462119748692606987": {},
				"473157580747702273": {},
				"478991912574124032": {},
				"578674706581028874": {},
				"596622031840083979": {},
				"617247386409893900": {},
				"690176399478489109": {},
				"691175890004082698": {},
				"927744068979683349": {},
				"582349391319400459": {}
			},
			"strangers": {}
		}
	},
	"852873259984093204": {
		"amounts": {
			"toastTime": 5,
			"checkInterval": 10
		},
		"dates": {
			"logDate": {}
		},
		"general": {
			"addOnlineCount": true,
			"showDiscriminator": false,
			"muteOnDND": false,
			"openOnClick": false
		},
		"notificationSounds": {
			"toastonline": {
				"url": null,
				"song": null,
				"mute": false
			},
			"desktoponline": {
				"url": null,
				"song": null,
				"mute": false
			},
			"toastidle": {
				"url": null,
				"song": null,
				"mute": false
			},
			"desktopidle": {
				"url": null,
				"song": null,
				"mute": false
			},
			"toastdnd": {
				"url": null,
				"song": null,
				"mute": false
			},
			"desktopdnd": {
				"url": null,
				"song": null,
				"mute": false
			},
			"toastplaying": {
				"url": null,
				"song": null,
				"mute": false
			},
			"desktopplaying": {
				"url": null,
				"song": null,
				"mute": false
			},
			"toastlistening": {
				"url": null,
				"song": null,
				"mute": false
			},
			"desktoplistening": {
				"url": null,
				"song": null,
				"mute": false
			},
			"toaststreaming": {
				"url": null,
				"song": null,
				"mute": false
			},
			"desktopstreaming": {
				"url": null,
				"song": null,
				"mute": false
			},
			"toastoffline": {
				"url": null,
				"song": null,
				"mute": false
			},
			"desktopoffline": {
				"url": null,
				"song": null,
				"mute": false
			}
		},
		"notificationStrings": {
			"online": "$user changed status to '$status'",
			"idle": "$user changed status to '$status'",
			"dnd": "$user changed status to '$status'",
			"playing": "$user started playing '$game'",
			"listening": "$user started listening to '$song'",
			"streaming": "$user started streaming '$game'",
			"offline": "$user changed status to '$status'",
			"login": "$user just logged in '$status'",
			"custom": "$user changed status to '$custom'"
		},
		"observed": {
			"friends": {},
			"strangers": {}
		}
	}
}